{
  "fabric:load_conditions": [
    {
      "condition": "fox_den:steel_armor"
    }
  ],
  "parent": "minecraft:recipes/root",
  "criteria": {
    "has_steel_blend": {
      "conditions": {
        "items": [
          {
            "items": "fox_den:steel_blend"
          }
        ]
      },
      "trigger": "minecraft:inventory_changed"
    },
    "has_the_recipe": {
      "conditions": {
        "recipe": "fox_den:steel_ingot"
      },
      "trigger": "minecraft:recipe_unlocked"
    }
  },
  "requirements": [
    [
      "has_the_recipe",
      "has_steel_blend"
    ]
  ],
  "rewards": {
    "recipes": [
      "fox_den:steel_ingot"
    ]
  }
}